hsbalance/IC_matrix.py
hsbalance/__init__.py
hsbalance/model.py
hsbalance/tools.py
hsbalance-0.5.5.dist-info/METADATA
hsbalance-0.5.5.dist-info/WHEEL
hsbalance-0.5.5.dist-info/top_level.txt
hsbalance-0.5.5.dist-info/RECORD
