Metadata-Version: 2.1
Name: hsbalance
Version: 0.5.5
Summary: Python tools for Practical Modeling and Solving High Speed Rotor Unbalance Problem
Home-page: https://github.com/MagedMohamedTurk/Turbomachinery-Rotors-Balancing
Author: Maged M.Eltorkoman
Author-email: newmaged@gmail.com
Project-URL: Bug Tracker, https://github.com/pypa/sampleproject/issues
Keywords: Optimization,Linear Programming,Integer Programming,Operations Research,Rotor Balance,Rotor Balancing,Vibration Analysis,Trim Balancing,Rotor Dynamics,Influence Coefficient Matrix Method,Convex Optimization,Field Engineering,Python3,CVXPY
Classifier: Programming Language :: Python :: 3
Classifier: License :: OSI Approved :: MIT License
Classifier: Operating System :: OS Independent
Requires-Python: >=3.8
Requires-Dist: cvxpy (>=1.1.18)
Requires-Dist: pandas (>=1.3.5)
Requires-Dist: cvxopt (>=1.2)
Requires-Dist: xpress (>=8)
